opbinario/__init__.py
opbinario/opbinario.py
opbinario-0.0.1.1.dist-info/LICENSE
opbinario-0.0.1.1.dist-info/METADATA
opbinario-0.0.1.1.dist-info/WHEEL
opbinario-0.0.1.1.dist-info/top_level.txt
opbinario-0.0.1.1.dist-info/RECORD
