Metadata-Version: 2.1
Name: opbinario
Version: 0.0.1.1
Summary: Pacote para realização de opereções com numeros binarios
Home-page: https://github.com/David-Marcoss/Opbinario
Author: David Marcos
Author-email: david.marcos54321@gmail.com
License: UNKNOWN
Platform: UNKNOWN
Classifier: Programming Language :: Python :: 3
Classifier: License :: OSI Approved :: MIT License
Classifier: Operating System :: OS Independent
Requires-Python: >=3.8
License-File: LICENSE
